difftorch/__init__.py
difftorch/difftorch.py
difftorch/util.py
difftorch-1.2.2.dist-info/LICENSE
difftorch-1.2.2.dist-info/METADATA
difftorch-1.2.2.dist-info/WHEEL
difftorch-1.2.2.dist-info/top_level.txt
difftorch-1.2.2.dist-info/RECORD
